README.md
setup.py
int_hash_int_hash_lib.egg-info/PKG-INFO
int_hash_int_hash_lib.egg-info/SOURCES.txt
int_hash_int_hash_lib.egg-info/dependency_links.txt
int_hash_int_hash_lib.egg-info/top_level.txt
int_hash_lib/__init__.py
int_hash_lib/utils/__init__.py
int_hash_lib/utils/default.py
int_hash_lib/utils/email.py
int_hash_lib/utils/ip_address.py
int_hash_lib/utils/normalizer.py
int_hash_lib/utils/phone.py
int_hash_lib/utils/user_agent.py