Metadata-Version: 1.0
Name: int-hash-int-hash-lib
Version: 0.0.2
Summary: int_hash_lib to hash data to int
Home-page: https://bitbucket.org/a_vento/int-hash-lib/src/master/
Author: MagicScore
Author-email: UNKNOWN
License: UNKNOWN
Platform: UNKNOWN
